mpl4qt/__init__.py
mpl4qt/config/default_mpl_settings.json
mpl4qt/examples/__init__.py
mpl4qt/examples/app1.py
mpl4qt/examples/app2.py
mpl4qt/examples/ui_app1.py
mpl4qt/examples/ui_app2.py
mpl4qt/launchers/__init__.py
mpl4qt/launchers/designer.py
mpl4qt/plugins/__init__.py
mpl4qt/plugins/mplbarplugin.py
mpl4qt/plugins/mplbaseplugin.py
mpl4qt/plugins/mplcurveplugin.py
mpl4qt/plugins/mplerrorbarplugin.py
mpl4qt/plugins/mplimageplugin.py
mpl4qt/ui/__init__.py
mpl4qt/ui/resources_rc.py
mpl4qt/ui/ui_fit_image.py
mpl4qt/ui/ui_kbdhelp.py
mpl4qt/ui/ui_markers_view.py
mpl4qt/ui/ui_mplconfig.py
mpl4qt/widgets/__init__.py
mpl4qt/widgets/_info.py
mpl4qt/widgets/_widgets.py
mpl4qt/widgets/fitting.py
mpl4qt/widgets/kbdhelpdialog.py
mpl4qt/widgets/markers_view.py
mpl4qt/widgets/mplbarwidget.py
mpl4qt/widgets/mplbasewidget.py
mpl4qt/widgets/mplconfig.py
mpl4qt/widgets/mplcurvewidget.py
mpl4qt/widgets/mplerrorbarwidget.py
mpl4qt/widgets/mplimagewidget.py
mpl4qt/widgets/mpltoolbar.py
mpl4qt/widgets/utils.py
mpl4qt-2.8.9.dist-info/LICENSE
mpl4qt-2.8.9.dist-info/METADATA
mpl4qt-2.8.9.dist-info/WHEEL
mpl4qt-2.8.9.dist-info/entry_points.txt
mpl4qt-2.8.9.dist-info/top_level.txt
mpl4qt-2.8.9.dist-info/RECORD
