Metadata-Version: 2.1
Name: mpl4qt
Version: 2.8.9
Summary: Data visualization widgets for PyQt5
Home-page: https://phantasy-project.github.io/mpl4qt/
Author: Tong Zhang
Author-email: zhangt@frib.msu.edu
License: MIT
Keywords: widgets Qt designer PyQt matplotlib
Platform: Linux
Classifier: Programming Language :: Python :: 3
Classifier: Topic :: Software Development :: Libraries :: Python Modules
Classifier: Topic :: Software Development :: User Interfaces
Classifier: Topic :: Scientific/Engineering :: Visualization
Requires-Dist: matplotlib
Requires-Dist: PyQt5
Requires-Dist: pandas
Requires-Dist: tzlocal
Provides-Extra: dev
Requires-Dist: pyqt5-tools; extra == "dev"
